<?xml version="1.0" encoding="utf-8"?>
<Maps>
  <Map Type="Ground_RWY" Name="ASMGCS_MMHO_RWY" Priority="1" Center="+290544.93-1110252.29">
    <!--RWY 05/23-->
    <Infill>
      <Point>
+290554.778-1110232.178/
+290515.989-1110344.943/
+290517.234-1110345.822/
+290556.051-1110233.035/
+290554.778-1110232.178</Point>
</Infill>
</Map>
<Map Type="Ground_TWY" Name="ASMGCS_MMHO_TWY" Priority="2" Center="+230915.8516-1094312.8125">
	<!--TWY A-->
	<Infill>
		<Point>
+290516.010-1110344.953/
+290514.260-1110343.747/
+290514.024-1110343.480/
+290513.860-1110343.216/
+290513.766-1110342.980/
+290513.697-1110342.724/
+290513.669-1110342.464/
+290513.678-1110341.989/
+290513.764-1110337.458/
+290513.784-1110337.238/
+290513.815-1110337.013/
+290513.854-1110336.810/
+290513.912-1110336.584/
+290514.020-1110336.293/
+290514.136-1110336.068/
+290514.306-1110335.738/
+290521.503-1110322.265/
+290521.550-1110322.059/
+290521.579-1110321.862/
+290521.581-1110321.646/
+290521.560-1110321.444/
+290521.499-1110321.247/
+290521.416-1110321.065/
+290521.347-1110320.936/
+290522.605-1110321.827/
+290514.901-1110336.289/
+290514.716-1110336.652/
+290514.619-1110336.951/
+290514.542-1110337.318/
+290514.447-1110342.245/
+290514.477-1110342.572/
+290514.551-1110342.778/
+290514.721-1110343.020/
+290514.911-1110343.159/
+290515.056-1110343.218/
+290515.158-1110343.123/
+290515.203-1110342.969/
+290515.303-1110342.735/
+290515.415-1110342.553/
+290515.547-1110342.404/
+290515.717-1110342.249/
+290515.932-1110342.129/
+290516.232-1110342.021/
+290517.409-1110341.633/
+290517.674-1110341.517/
+290517.857-1110341.382/
+290517.994-1110341.246/
+290516.010-1110344.953</Point>
</Infill>
<Infill>
	<Point>
<!--TWY B-->
+290525.573-1110327.068/
+290525.851-1110326.345/
+290525.989-1110325.864/
+290526.093-1110325.397/
+290526.183-1110324.862/
+290526.236-1110324.466/
+290526.265-1110324.145/
+290526.416-1110315.941/
+290526.325-1110315.749/
+290526.183-1110315.653/
+290526.043-1110315.650/
+290525.944-1110315.686/
+290525.825-1110315.738/
+290527.494-1110312.647/
+290527.434-1110312.824/
+290527.351-1110313.063/
+290527.278-1110313.320/
+290527.242-1110313.560/
+290527.215-1110313.795/
+290527.206-1110314.191/
+290527.073-1110320.518/
+290527.113-1110320.695/
+290527.195-1110320.919/
+290527.317-1110321.120/
+290527.464-1110321.263/
+290527.752-1110321.430/
+290527.950-1110321.461/
+290528.149-1110321.484/
+290528.321-1110321.434/
+290528.455-1110321.356/
+290528.713-1110321.150/
+290525.573-1110327.068</Point>
</Infill>
<Infill>
	<Point>
<!--TWY C-->
+290530.392-1110303.388/
+290531.843-1110304.492/
+290535.680-1110257.317/
+290535.787-1110257.199/
+290535.913-1110257.129/
+290536.038-1110257.119/
+290536.157-1110257.142/
+290539.271-1110300.631/
+290539.327-1110300.759/
+290539.357-1110300.929/
+290539.351-1110301.119/
+290539.350-1110301.185/
+290540.102-1110259.808/
+290539.954-1110259.884/
+290539.855-1110259.908/
+290539.763-1110259.903/
+290539.651-1110259.853/
+290539.523-1110259.743/
+290538.307-1110258.389/
+290538.183-1110258.241/
+290538.115-1110258.034/
+290538.004-1110256.467/
+290534.752-1110256.718/
+290534.864-1110256.813/
+290534.911-1110256.909/
+290534.929-1110257.023/
+290534.897-1110257.105/
+290531.730-1110303.074/
+290531.475-1110303.380/
+290531.293-1110303.500/
+290531.078-1110303.565/
+290530.866-1110303.581/
+290530.617-1110303.509/
+290530.392-1110303.388</Point>
</Infill>
<Infill>
	<Point>
<!--TWY D-->
+290537.561-1110248.354/
+290536.507-1110246.665/
+290536.675-1110246.689/
+290536.812-1110246.623/
+290536.906-1110246.518/
+290538.882-1110244.462/
+290539.155-1110244.136/
+290539.609-1110243.469/
+290540.142-1110242.649/
+290544.857-1110235.099/
+290544.889-1110235.002/
+290544.895-1110234.919/
+290544.865-1110234.818/
+290544.814-1110234.751/
+290544.741-1110234.702/
+290544.627-1110234.657/
+290541.658-1110234.031/
+290541.789-1110233.158/
+290545.262-1110233.920/
+290545.451-1110233.930/
+290545.590-1110233.871/
+290545.729-1110233.767/
+290548.205-1110229.875/
+290548.421-1110229.644/
+290548.707-1110229.387/
+290549.029-1110229.219/
+290549.296-1110229.137/
+290549.576-1110229.100/
+290549.891-1110229.104/
+290550.237-1110229.182/
+290550.462-1110229.272/
+290550.689-1110229.407/
+290554.788-1110232.219/
+290554.238-1110233.258/
+290554.220-1110233.070/
+290554.174-1110232.905/
+290554.118-1110232.776/
+290554.008-1110232.664/
+290550.301-1110230.115/
+290550.063-1110229.987/
+290549.815-1110229.940/
+290549.554-1110229.930/
+290549.267-1110230.008/
+290549.047-1110230.150/
+290548.859-1110230.310/
+290548.731-1110230.475/
+290540.166-1110244.020/
+290539.911-1110244.400/
+290539.669-1110244.721/
+290539.353-1110245.087/
+290538.528-1110245.958/
+290537.640-1110246.872/
+290537.547-1110247.079/
+290537.521-1110247.243/
+290537.586-1110248.354/
+290537.561-1110248.354</Point>
</Infill>
</Map>
  <Map Type="Ground_APR" Name="ASMGCS_MMHO_APR" Priority="3" Center="+290544.93-1110252.29">
    <!--Comercial-->
    <Infill>
      <Point>
+290518.630-1110318.963/
+290521.277-1110320.838/
+290521.338-1110320.922/
+290521.360-1110320.971/
+290522.587-1110321.870/
+290525.862-1110315.708/
+290527.552-1110312.569/
+290531.867-1110304.469/
+290528.538-1110302.023/
+290520.701-1110316.755/
+290520.052-1110316.297/
+290518.630-1110318.963</Point>
</Infill>
    <!--Av Gral-->
    <Infill>
      <Point>
+290538.006-1110256.489/
+290534.761-1110256.739/
+290534.453-1110256.437/
+290533.994-1110248.338/
+290530.534-1110242.795/
+290534.486-1110239.607/
+290537.540-1110244.486/
+290535.973-1110245.760/
+290536.539-1110246.683/
+290537.584-1110248.351/
+290538.006-1110256.489</Point>
</Infill>
    <!--FAM-->
    <Infill>
      <Point>
+290538.681-1110239.919/
+290539.861-1110232.057/
+290541.918-1110232.488/
+290541.124-1110237.441/
+290540.537-1110237.309/
+290540.502-1110237.578/
+290539.913-1110237.447/
+290539.384-1110240.065/
+290538.681-1110239.919/</Point>
</Infill>
</Map>
<Map Type="Ground_BLD" Name="ASMGCS_MMHO_BLD" Priority="1" Center="+290544.93-1110252.29">
    <!--Terminal-->
    <Infill>
      <Point>
+290523.657-1110310.541/
+290522.085-1110309.461/
+290524.840-1110303.896/
+290526.128-1110304.855/
+290526.041-1110305.041/
+290526.139-1110305.095/
+290525.488-1110306.294/
+290525.751-1110306.505/
+290523.657-1110310.541/</Point>
</Infill>
    <!--Hangar 1-->
    <Infill>
      <Point>
+290533.728-1110254.553/
+290533.267-1110254.563/
+290533.256-1110254.230/
+290533.303-1110254.202/
+290533.242-1110252.536/
+290533.176-1110252.538/
+290533.185-1110252.042/
+290533.672-1110251.980/
+290533.728-1110254.553</Point>
</Infill>
    <!--Hangar 2-->
    <Infill>
      <Point>
+290530.751-1110249.622/
+290532.506-1110248.220/
+290532.874-1110248.881/
+290531.814-1110249.671/
+290531.905-1110249.821/
+290531.202-1110250.378/
+290530.751-1110249.622</Point>
</Infill>
    <!--Hangar 3-->
    <Infill>
      <Point>
+290530.634-1110248.692/
+290530.130-1110247.891/
+290531.975-1110246.396/
+290532.470-1110247.204/
+290530.634-1110248.692</Point>
</Infill>
    <!--Hangar 4-->
    <Infill>
      <Point>
+290529.758-1110246.926/
+290529.282-1110246.132/
+290530.940-1110244.727/
+290531.483-1110245.556/
+290529.758-1110246.926</Point>
</Infill>
    <!--Hangar 5-->
    <Infill>
      <Point>
+290528.518-1110245.699/
+290528.023-1110244.867/
+290529.958-1110243.330/
+290530.415-1110244.109/
+290528.518-1110245.699</Point>
</Infill>
    <!--Hangar FAM 1-->
    <Infill>
      <Point>
+290538.528-1110239.870/
+290536.955-1110239.520/
+290537.288-1110237.251/
+290538.883-1110237.592/
+290538.528-1110239.870</Point>
</Infill>
    <!--Hangar FAM 2-->
    <Infill>
      <Point>
+290539.106-1110236.735/
+290537.781-1110236.443/
+290538.178-1110233.973/
+290539.527-1110234.275/
+290539.106-1110236.735</Point>
</Infill>
</Map>
<Map Type="Ground_RWY" Name="ASMGCS_MMHO_LABELS" CustomColourName="GroundLabel" Priority="1" Center="+290544.93-1110252.29">
   <Label HasLeader="false">
      <Point Name="A">+290518.6953-1110332.4063</Point>
      <Point Name="A">+290531.7969-1110306.7813</Point>
      <Point Name="B">+290528.2656-1110317.6563</Point>
      <Point Name="C">+290537.5313-1110300.7813</Point>
      <Point Name="D">+290538.9922-1110251.0938</Point>
      <Point Name="D">+290544.5625-1110239.8125</Point>
      <Point Name="D">+290553.4609-1110228.2813</Point>
    </Label>
    </Map>
</Maps>