<?xml version="1.0" encoding="utf-8"?>
<Maps>
  <Map Type="System" Name="ALL_ROUTES_LOW" Priority="1" Center="+204657.054-0865400.018">
    <Line Name="A317">TAP.A317.TECUN</Line>
    <Line Name="A552">TAM.A552.GABEN</Line>
    <Line Name="A758">MID.A758.VIDNO</Line>
    <Line Name="A766">KEHLI.A766.SIGMA</Line>
    <Line Name="A770">KEHLI.A770.UKORO</Line>
    <Line Name="B646">LENUK.B646.MID</Line>
    <Line Name="B753">MID.B753.PIKRO</Line>
    <Line Name="B764">EMOSA.B764.ANEPU</Line>
    <Line Name="B879">NOSAT.B879.CZM</Line>
    <Line Name="B881">CUN.B881.ANIKO</Line>
    <Line Name="G521">CZM.G521.AMIDA</Line>
    <Line Name="G633">VSA.G633.EMADA</Line>
    <Line Name="G757">CTM.G757.KINAL</Line>
    <Line Name="G765">NUKAN.G765.CTM</Line>
    <Line Name="R506">NUDAL.R506.CUN</Line>
    <Line Name="R522">ALURU.R522.PAZ</Line>
    <Line Name="V1">TIJ.V1.CME</Line>
    <Line Name="V1E">LTO.V1E.SJD</Line>
    <Line Name="V1W">LTO.V1W.SJD</Line>
    <Line Name="V2">CUU.V2.MAM</Line>
    <Line Name="V3">TIJ.V3.CUN</Line>
    <Line Name="V4">LTO.V4.SJD</Line>
    <Line Name="V5">CUL.V5.CUA</Line>
    <Line Name="V6">TTM.V6.TAM</Line>
    <Line Name="V7">ENS.V7.CEN</Line>
    <Line Name="V8">LMM.V8.LAP</Line>
    <Line Name="V9">CEN.V9.CSL</Line>
    <Line Name="V10">MAM.V10.LAP</Line>
    <Line Name="V11">TRC.V11.ZIH</Line>
    <Line Name="V12">CVM.V12.LTO</Line>
    <Line Name="V13">REX.V13.MTY</Line>
    <Line Name="V14">PVR.V14.QET</Line>
    <Line Name="V14N">PVR.V14N.GDL</Line>
    <Line Name="V14S">PVR.V14S.GDL</Line>
    <Line Name="V15">PNG.V15.ACA</Line>
    <Line Name="V15E">TEQ.V15E.ACA</Line>
    <Line Name="V15W">TEQ.V15W.ACA</Line>
    <Line Name="V16">AGU.V16.MID</Line>
    <Line Name="V17">TAM.V17.UPN</Line>
    <Line Name="V18">PAZ.V18.ZLO</Line>
    <Line Name="V19">NLD.V19.APN</Line>
    <Line Name="V20">NLD.V20.LAP</Line>
    <Line Name="V21">REX.V21.ACA</Line>
    <Line Name="V22">AGU.V22.CMT</Line>
    <Line Name="V23">MOV.V23.CMT</Line>
    <Line Name="V24">CUA.V24.ZIH</Line>
    <Line Name="V25">MAM.V25.CUA</Line>
    <Line Name="V26">NLD.V26.ZLO</Line>
    <Line Name="V26W">GDL.V26W.ZLO</Line>
    <Line Name="V27">LTO.V27.HUX</Line>
    <Line Name="V27E">OAX.V27E.HUX</Line>
    <Line Name="V28">MLM.V28.CTM</Line>
    <Line Name="V29">PAZ.V29.PXM</Line>
    <Line Name="V30">CZM.V30.CME</Line>
    <Line Name="V31">MTT.V31.IZT</Line>
    <Line Name="V32">GDL.V32.TEQ</Line>
    <Line Name="V33">VER.V33.IZT</Line>
    <Line Name="V34">PAZ.V34.UPN</Line>
    <Line Name="V35">MTY.V35.REX</Line>
    <Line Name="V36">CPE.V36.CTM</Line>
    <Line Name="V37">NLD.V37.PVR</Line>
    <Line Name="V38">PERGO.V38.CTM</Line>
    <Line Name="V39">PNG.V39.ZIH</Line>
    <Line Name="V39E">SLP.V39E.BJX</Line>
    <Line Name="V40">MXL.V40.HMO</Line>
    <Line Name="V41">TIJ.V41.SJD</Line>
    <Line Name="V42">TIJ.V42.CEN</Line>
    <Line Name="V43">MAM.V43.HUX</Line>
    <Line Name="V44">MID.V44.CUN</Line>
    <Line Name="V45">MID.V45.CZM</Line>
    <Line Name="V46">AGU.V46.ZIH</Line>
    <Line Name="V47">TRC.V47.TAM</Line>
    <Line Name="V49">NLD.V49.ZIH</Line>
    <Line Name="V51">VSA.V51.TAP</Line>
    <Line Name="V52">LMM.V52.SJD</Line>
    <Line Name="V53">CEN.V53.MZT</Line>
    <Line Name="V54">PCA.V54.VER</Line>
    <Line Name="V55">PNG.V55.CVM</Line>
    <Line Name="V56">CUN.V56.CPE</Line>
    <Line Name="V57">SJD.V57.CUL</Line>
    <Line Name="V58">MXL.V58.ENS</Line>
    <Line Name="V59">CUA.V59.MAXUL</Line>
    <Line Name="V61">SLP.V61.COL</Line>
    <Line Name="V61W">AGU.V61W.GDL</Line>
    <Line Name="V63">TTM.V63.PTJ</Line>
    <Line Name="V64">MTY.V64.MAM</Line>
    <Line Name="V68">NLD.V68.SLW</Line>
    <Line Name="V70">BRO.V70.MTY</Line>
    <Line Name="V81">ALKEM.V81.CUU</Line>
    <Line Name="V83">PNG.V83.SLW</Line>
    <Line Name="V135">BZA.V135.TIJ</Line>
    <Line Name="V137">IPL.V137.MXL</Line>
    <Line Name="V163">BRO.V163.MAM</Line>
    <Line Name="V280">ELP.V280.CUU</Line>
    <Line Name="V359">LRD.V359.NLD</Line>
    <Line Name="V387">MFE.V387.TAM</Line>
    <Line Name="V393">OLS.V393.SJD</Line>
    <Line Name="V625">OLS.V625.HMO</Line>
    <Symbol Type="HollowSquare">
      <!--MMID-->
      <Point>MTT</Point>
      <Point>IZT</Point>
      <Point>VSA</Point>
      <Point>TGZ</Point>
      <Point>TAP</Point>
      <Point>CME</Point>
      <Point>CTM</Point>
      <Point>CPE</Point>
      <Point>MID</Point>
      <Point>CZA</Point>
      <Point>CZM</Point>
      <Point>CUN</Point>
    </Symbol>
    <Symbol Type="Circle">
      <!--MMEX-->
      <Point>ZCL</Point>
      <Point>SLP</Point>
      <Point>TTM</Point>
      <Point>TMN</Point>
      <Point>TAM</Point>
      <Point>AGU</Point>
      <Point>BJX</Point>
      <Point>QET</Point>
      <Point>PAZ</Point>
      <Point>PVR</Point>
      <Point>GDL</Point>
      <Point>MLM</Point>
      <Point>VER</Point>
      <Point>ZLO</Point>
      <Point>COL</Point>
      <Point>UPN</Point>
      <Point>ZIH</Point>
      <Point>ACA</Point>
      <Point>OAX</Point>
      <Point>PXM</Point>
      <Point>PXM</Point>
      <Point>HUX</Point>
      <Point>SLM</Point>
      <Point>SMO</Point>
      <Point>APN</Point>
      <Point>PTJ</Point>
      <Point>TLC</Point>
      <Point>MEX</Point>
      <Point>PBC</Point>
      <Point>CVJ</Point>
      <Point>TEQ</Point>
      <Point>CUA</Point>
    </Symbol>
    <Symbol Type="SolidTriangle">
    </Symbol>
    <Symbol Type="HollowTriangle">
    </Symbol>
    <Symbol Type="SolidTriangleWithBorder">
    </Symbol>
    <Symbol Type="HollowTriangleWithBorder">
    </Symbol>
  </Map>
  <Map Type="System" Name="ALL_POINTS_LOW" Priority="1" Center="+204657.054-0865400.018">
    <Label HasLeader="false">
      <!--MMEX-->
      <Point>ZCL</Point>
      <Point>SLP</Point>
      <Point>TTM</Point>
      <Point>TMN</Point>
      <Point>TAM</Point>
      <Point>AGU</Point>
      <Point>BJX</Point>
      <Point>QET</Point>
      <Point>PAZ</Point>
      <Point>PVR</Point>
      <Point>GDL</Point>
      <Point>MLM</Point>
      <Point>VER</Point>
      <Point>ZLO</Point>
      <Point>COL</Point>
      <Point>UPN</Point>
      <Point>ZIH</Point>
      <Point>ACA</Point>
      <Point>OAX</Point>
      <Point>PXM</Point>
      <Point>PXM</Point>
      <Point>HUX</Point>
      <Point>SLM</Point>
      <Point>SMO</Point>
      <Point>APN</Point>
      <Point>PTJ</Point>
      <Point>TLC</Point>
      <Point>MEX</Point>
      <Point>PBC</Point>
      <Point>CVJ</Point>
      <Point>TEQ</Point>
      <Point>CUA</Point>
    </Label>
  </Map>
  <Map Type="System" Name="ALL_ROUTES_HIGH" Priority="1" Center="+204657.054-0865400.018">
    <Line Name="J1">MZB.J1.TAP</Line>
    <Line Name="J13">TCS.J13.TAP</Line>
    <Line Name="J21">LRD.J21.ACA</Line>
    <Line Name="J22">LRD.J22.NLD</Line>
    <Line Name="J25">BRO.J25.COL</Line>
    <Line Name="J26">ELP.J26.HMO</Line>
    <Line Name="J29">DEVOE.J29.SJD</Line>
    <Line Name="J42">FST.J42.TLC</Line>
    <Line Name="J92">TUS.J92.LAP</Line>
    <Line Name="J93">JLI.J93.PPE</Line>
    <Line Name="J141">KEYLO.J141.ZLO</Line>
    <Line Name="J177">KANNA.J177.ZIH</Line>
    <Line Name="UA317">TAP.UA317.TECUN</Line>
    <Line Name="UA552">VER.UA552.GABEN</Line>
    <Line Name="UA758">MID.UA758.VIDNO</Line>
    <Line Name="UA766">KEHLI.UA766.SIGMA</Line>
    <Line Name="UA770">KEHLI.UA770.UKORO</Line>
    <Line Name="UB646">LENUK.UB646.MID</Line>
    <Line Name="UB753">MID.UB753.PIKRO</Line>
    <Line Name="UB764">EMOSA.UB764.ANEPU</Line>
    <Line Name="UB879">NOSAT.UB879.CZM</Line>
    <Line Name="UB881">CUN.UB881.ANIKO</Line>
    <Line Name="UG521">CZM.UG521.AMIDA</Line>
    <Line Name="UG757">CTM.UG757.KINAL</Line>
    <Line Name="UG765">NUKAN.UG765.CTM</Line>
    <Line Name="UJ1E">LTO.UJ1E.LAP</Line>
    <Line Name="UJ2">LTO.UJ2.MAM</Line>
    <Line Name="UJ3">TIJ.UJ3.ACA</Line>
    <Line Name="UJ4">ELQ.UJ4.MAM</Line>
    <Line Name="UJ5">DGO.UJ5.CTM</Line>
    <Line Name="UJ7">TIJ.UJ7.ZIH</Line>
    <Line Name="UJ8">LMM.UJ8.LAP</Line>
    <Line Name="UJ9">LTO.UJ9.CZM</Line>
    <Line Name="UJ10">MAM.UJ10.LAP</Line>
    <Line Name="UJ11">NLD.UJ11.ZLO</Line>
    <Line Name="UJ11E">NLD.UJ11E.MTY</Line>
    <Line Name="UJ12">CUL.UJ12.VSA</Line>
    <Line Name="UJ12S">GDL.UJ12S.TNY</Line>
    <Line Name="UJ13">REX.UJ13.MTY</Line>
    <Line Name="UJ14">CEN.UJ14.TAM</Line>
    <Line Name="UJ14N">PVR.UJ14N.GDL</Line>
    <Line Name="UJ14S">PVR.UJ14S.GDL</Line>
    <Line Name="UJ15">XOXIL.UJ15.ACA</Line>
    <Line Name="UJ15E">MTY.UJ15E.CVM</Line>
    <Line Name="UJ16">CUN.UJ16.ACA</Line>
    <Line Name="UJ16W">CPE.UJ16W.MID</Line>
    <Line Name="UJ17">REX.UJ17.ZIH</Line>
    <Line Name="UJ18">URTOK.UJ18.ZLO</Line>
    <Line Name="UJ19">MAM.UJ19.PXM</Line>
    <Line Name="UJ20">TIJ.UJ20.NLD</Line>
    <Line Name="UJ21E">TEQ.UJ21E.ACA</Line>
    <Line Name="UJ21W">TEQ.UJ21W.ACA</Line>
    <Line Name="UJ23">LMM.UJ23.SJD</Line>
    <Line Name="UJ24">CZM.UJ24.UPN</Line>
    <Line Name="UJ24S">ZIH.UJ24S.TEQ</Line>
    <Line Name="UJ25">CME.UJ25.TGZ</Line>
    <Line Name="UJ26">PERGO.UJ26.CTM</Line>
    <Line Name="UJ27">CJS.UJ27.ZIH</Line>
    <Line Name="UJ28">APN.UJ28.CTM</Line>
    <Line Name="UJ30">TLC.UJ30.ZIH</Line>
    <Line Name="UJ31">PNG.UJ31.BJX</Line>
    <Line Name="UJ32">MTY.UJ32.SJD</Line>
    <Line Name="UJ33">CUL.UJ33.HUX</Line>
    <Line Name="UJ34">VER.UJ34.IZT</Line>
    <Line Name="UJ35">MAM.UJ35.SLM</Line>
    <Line Name="UJ36">TTM.UJ36.TMN</Line>
    <Line Name="UJ37">TRC.UJ37.PVR</Line>
    <Line Name="UJ38">HMO.UJ38.APN</Line>
    <Line Name="UJ39">PAZ.UJ39.HUX</Line>
    <Line Name="UJ40">NLD.UJ40.MLM</Line>
    <Line Name="UJ41">NLD.UJ41.VER</Line>
    <Line Name="UJ45">PNG.UJ45.ACA</Line>
    <Line Name="UJ46">CJS.UJ46.TAM</Line>
    <Line Name="UJ47">CJS.UJ47.TAP</Line>
    <Line Name="UJ48">CSL.UJ48.PVR</Line>
    <Line Name="UJ50">ZCL.UJ50.SLP</Line>
    <Line Name="UJ52">CUN.UJ52.ILUBA</Line>
    <Line Name="UJ53">REX.UJ53.TAM</Line>
    <Line Name="UJ54">CJS.UJ54.CUL</Line>
    <Line Name="UJ55">PAZ.UJ55.SLM</Line>
    <Line Name="UJ61">CPE.UJ61.CTM</Line>
    <Line Name="UJ63">DGO.UJ63.MLM</Line>
    <Line Name="UJ64">TLC.UJ64.MTT</Line>
    <Line Name="UJ65">UPN.UJ65.MEX</Line>
    <Line Name="UJ68">NLD.UJ68.SLW</Line>
    <Line Name="UJ69">OAX.UJ69.PXM</Line>
    <Line Name="UJ70">VER.UJ70.HUX</Line>
    <Line Name="UJ71">TEQ.UJ71.PXM</Line>
    <Line Name="UJ81">MTY.UJ81.CUA</Line>
    <Line Name="UJ83">PNG.UJ83.SLW</Line>
    <Line Name="UJ84">CUN.UJ84.CPE</Line>
    <Line Name="UJ95">PCA.UJ95.APN</Line>
    <Line Name="UJ102">PAZ.UJ102.PCA</Line>
    <Line Name="UR506">NUDAL.UR506.CUN</Line>
    <Line Name="UR522">ALURU.UR522.PAZ</Line>
    <Line Name="UR644">TAP.UR644.IMASO</Line>
    <Line Name="UR899">CTM.UR899.ULEVA</Line>
    <Symbol Type="HollowSquare">
      <!--MMID-->
      <Point>MTT</Point>
      <Point>IZT</Point>
      <Point>VSA</Point>
      <Point>TGZ</Point>
      <Point>TAP</Point>
      <Point>CME</Point>
      <Point>CTM</Point>
      <Point>CPE</Point>
      <Point>MID</Point>
      <Point>CZA</Point>
      <Point>CZM</Point>
      <Point>CUN</Point>

      <!--MMEX-->
      <Point>ZCL</Point>
      <Point>SLP</Point>
      <Point>TTM</Point>
      <Point>TMN</Point>
      <Point>TAM</Point>
      <Point>AGU</Point>
      <Point>BJX</Point>
      <Point>QET</Point>
      <Point>PAZ</Point>
      <Point>PVR</Point>
      <Point>GDL</Point>
      <Point>MLM</Point>
      <Point>VER</Point>
      <Point>ZLO</Point>
      <Point>COL</Point>
      <Point>UPN</Point>
      <Point>ZIH</Point>
      <Point>ACA</Point>
      <Point>OAX</Point>
      <Point>PXM</Point>
      <Point>PXM</Point>
      <Point>HUX</Point>
      <Point>SLM</Point>
      <Point>SMO</Point>
      <Point>APN</Point>
      <Point>PTJ</Point>
      <Point>TLC</Point>
      <Point>MEX</Point>
      <Point>PBC</Point>
      <Point>CVJ</Point>
      <Point>TEQ</Point>
      <Point>CUA</Point>
    </Symbol>
    <Symbol Type="Circle">
      <!--MMID-->
      <Point>MTT</Point>
      <Point>IZT</Point>
      <Point>VSA</Point>
      <Point>TGZ</Point>
      <Point>TAP</Point>
      <Point>CME</Point>
      <Point>CTM</Point>
      <Point>CPE</Point>
      <Point>MID</Point>
      <Point>CZA</Point>
      <Point>CZM</Point>
      <Point>CUN</Point>

      <!--MMEX-->
      <Point>ZCL</Point>
      <Point>SLP</Point>
      <Point>TTM</Point>
      <Point>TMN</Point>
      <Point>TAM</Point>
      <Point>AGU</Point>
      <Point>BJX</Point>
      <Point>QET</Point>
      <Point>PAZ</Point>
      <Point>PVR</Point>
      <Point>GDL</Point>
      <Point>MLM</Point>
      <Point>VER</Point>
      <Point>ZLO</Point>
      <Point>COL</Point>
      <Point>UPN</Point>
      <Point>ZIH</Point>
      <Point>ACA</Point>
      <Point>OAX</Point>
      <Point>PXM</Point>
      <Point>PXM</Point>
      <Point>HUX</Point>
      <Point>SLM</Point>
      <Point>SMO</Point>
      <Point>APN</Point>
      <Point>PTJ</Point>
      <Point>TLC</Point>
      <Point>MEX</Point>
      <Point>PBC</Point>
      <Point>CVJ</Point>
      <Point>TEQ</Point>
      <Point>CUA</Point>
    </Symbol>
    <Symbol Type="SolidTriangle">
      <Point>AXOMU</Point>
      <Point>ANEPU</Point>
      <Point>KEHLI</Point>
      <Point>OMPAN</Point>
      <Point>GOTAS</Point>
      <Point>NOREL</Point>
      <Point>ELOGO</Point>
      <Point>DUPLO</Point>
      <Point>AVTUD</Point>
      <Point>XORUV</Point>
      <Point>OMATO</Point>
      <Point>XOPVO</Point>
      <Point>AVINA</Point>
      <Point>XOSLO</Point>
      <Point>DURDO</Point>
      <Point>LENUK</Point>
      <Point>ALURU</Point>
      <Point>NOSAT</Point>
      <Point>EMOSA</Point>
      <Point>URTOK</Point>
      <Point>NUKAN</Point>
      <Point>NUDAL</Point>
      <Point>ILUBA</Point>
      <Point>SIGMA</Point>
      <Point>ANIKO</Point>
      <Point>AMIDA</Point>
      <Point>TUGET</Point>
      <Point>VIDNO</Point>
      <Point>UKORO</Point>
      <Point>GABEN</Point>
      <Point>IMASO</Point>
      <Point>TECUN</Point>
      <Point>ONGIG</Point>
      <Point>NUDIK</Point>
      <Point>DUSOK</Point>
      <Point>NOSOS</Point>
      <Point>DUPAS</Point>
      <Point>MESNA</Point>
      <Point>MUXOG</Point>
      <Point>DAXOL</Point>
      <Point>RORLA</Point>
      <Point>TABSA</Point>
      <Point>SUVUM</Point>
      <Point>DUSOV</Point>
      <Point>DYSON</Point>
      <Point>XUDUN</Point>
      <Point>AXIMA</Point>
      <Point>DUTKA</Point>
      <Point>IPSUM</Point>

      <Point>AVOMA</Point>
      <Point>CAEAR</Point>
      <Point>CANOZ</Point>
      <Point>DYSON</Point>
      <Point>ELSIP</Point>
      <Point>GABOB</Point>
      <Point>ILELA</Point>
      <Point>LIFTS</Point>
      <Point>NAPRI</Point>
      <Point>XUBSU</Point>
      <Point>ISARO</Point>
      <Point>XUBSU</Point>
      <Point>VIVEP</Point>
      <Point>VOMAR</Point>
      <Point>PAULE</Point>

      <!--MMEX-->
      <Point>LIDED</Point>
      <Point>NUBEL</Point>
      <Point>MUXEP</Point>
      <Point>COPOS</Point>
      <Point>OMPUT</Point>
      <Point>ALITA</Point>
      <Point>ALMET</Point>
      <Point>REXES</Point>
      <Point>MEBAS</Point>
      <Point>MISAS</Point>
      <Point>RETOM</Point>
      <Point>PIVOL</Point>
      <Point>XOSOK</Point>
      <Point>LEXOR</Point>
      <Point>XOPMA</Point>
      <Point>ULUAS</Point>
      <Point>AVSUB</Point>
      <Point>DUPUD</Point>
      <Point>OTRUD</Point>
      <Point>ROGDI</Point>
      <Point>PIGVU</Point>
      <Point>GABLI</Point>
      <Point>MITIN</Point>
      <Point>IMOSO</Point>
      <Point>RABIL</Point>
      <Point>GOYAS</Point>
      <Point>ANILA</Point>
      <Point>MANTA</Point>
      <Point>ONBIK</Point>
      <Point>FRESA</Point>
      <Point>URVEM</Point>
      <Point>XOSUD</Point>
      <Point>XOSAS</Point>
      <Point>XOTKI</Point>
      <Point>TIKEB</Point>
      <Point>SASUT</Point>
      <Point>AVSAR</Point>
      <Point>DATUL</Point>
    </Symbol>
    <Symbol Type="HollowTriangle">
      <Point>SILAC</Point>
      <Point>MORAS</Point>
      <Point>LLANO</Point>
      <Point>HORTA</Point>
      <Point>ERBOS</Point>
    </Symbol>
    <Symbol Type="SolidStar">
      <Point>TAJIN</Point>
      <Point>URLIX</Point>
      <Point>AVALI</Point>
      <Point>RAULS</Point>
      <Point>OTUDI</Point>
      <Point>COAPA</Point>
      <Point>UKROR</Point>
    </Symbol>
  </Map>
  <Map Type="System" Name="ALL_POINTS_HIGH" Priority="1" Center="+204657.054-0865400.018">
    <Label HasLeader="false">
      <!--MMID-->
      <Point>MTT</Point>
      <Point>IZT</Point>
      <Point>VSA</Point>
      <Point>TGZ</Point>
      <Point>TAP</Point>
      <Point>CME</Point>
      <Point>CTM</Point>
      <Point>CPE</Point>
      <Point>MID</Point>
      <Point>CZA</Point>
      <Point>CZM</Point>
      <Point>CUN</Point>

      <Point>AXOMU</Point>
      <Point>ANEPU</Point>
      <Point>KEHLI</Point>
      <Point>OMPAN</Point>
      <Point>GOTAS</Point>
      <Point>NOREL</Point>
      <Point>ELOGO</Point>
      <Point>DUPLO</Point>
      <Point>AVTUD</Point>
      <Point>XORUV</Point>
      <Point>OMATO</Point>
      <Point>XOPVO</Point>
      <Point>AVINA</Point>
      <Point>XOSLO</Point>
      <Point>DURDO</Point>
      <Point>LENUK</Point>
      <Point>ALURU</Point>
      <Point>NOSAT</Point>
      <Point>EMOSA</Point>
      <Point>URTOK</Point>
      <Point>NUKAN</Point>
      <Point>NUDAL</Point>
      <Point>ILUBA</Point>
      <Point>SIGMA</Point>
      <Point>ANIKO</Point>
      <Point>AMIDA</Point>
      <Point>TUGET</Point>
      <Point>VIDNO</Point>
      <Point>UKORO</Point>
      <Point>GABEN</Point>
      <Point>IMASO</Point>
      <Point>TECUN</Point>
      <Point>ONGIG</Point>
      <Point>NUDIK</Point>
      <Point>DUSOK</Point>
      <Point>NOSOS</Point>
      <Point>DUPAS</Point>
      <Point>MESNA</Point>
      <Point>MUXOG</Point>
      <Point>DAXOL</Point>
      <Point>RORLA</Point>
      <Point>TABSA</Point>
      <Point>SUVUM</Point>
      <Point>DUSOV</Point>
      <Point>DYSON</Point>
      <Point>XUDUN</Point>
      <Point>AXIMA</Point>
      <Point>DUTKA</Point>
      <Point>IPSUM</Point>

      <Point>AVOMA</Point>
      <Point>CAEAR</Point>
      <Point>CANOZ</Point>
      <Point>DYSON</Point>
      <Point>ELSIP</Point>
      <Point>GABOB</Point>
      <Point>ILELA</Point>
      <Point>LIFTS</Point>
      <Point>NAPRI</Point>
      <Point>XUBSU</Point>
      <Point>ISARO</Point>
      <Point>XUBSU</Point>
      <Point>VIVEP</Point>

      <Point>VOMAR</Point>
      <Point>PAULE</Point>

      <!--MMEX-->
      <Point>ZCL</Point>
      <Point>SLP</Point>
      <Point>TTM</Point>
      <Point>TMN</Point>
      <Point>TAM</Point>
      <Point>AGU</Point>
      <Point>BJX</Point>
      <Point>QET</Point>
      <Point>PAZ</Point>
      <Point>PVR</Point>
      <Point>GDL</Point>
      <Point>MLM</Point>
      <Point>VER</Point>
      <Point>ZLO</Point>
      <Point>COL</Point>
      <Point>UPN</Point>
      <Point>ZIH</Point>
      <Point>ACA</Point>
      <Point>OAX</Point>
      <Point>PXM</Point>
      <Point>PXM</Point>
      <Point>HUX</Point>
      <Point>SLM</Point>
      <Point>SMO</Point>
      <Point>APN</Point>
      <Point>PTJ</Point>
      <Point>TLC</Point>
      <Point>MEX</Point>
      <Point>PBC</Point>
      <Point>CVJ</Point>
      <Point>TEQ</Point>
      <Point>CUA</Point>

      <!--MMEX-->
      <Point>LIDED</Point>
      <Point>NUBEL</Point>
      <Point>MUXEP</Point>
      <Point>COPOS</Point>
      <Point>OMPUT</Point>
      <Point>ALITA</Point>
      <Point>ALMET</Point>
      <Point>REXES</Point>
      <Point>MEBAS</Point>
      <Point>MISAS</Point>
      <Point>RETOM</Point>
      <Point>PIVOL</Point>
      <Point>XOSOK</Point>
      <Point>LEXOR</Point>
      <Point>XOPMA</Point>
      <Point>ULUAS</Point>
      <Point>AVSUB</Point>
      <Point>DUPUD</Point>
      <Point>OTRUD</Point>
      <Point>ROGDI</Point>
      <Point>PIGVU</Point>
      <Point>GABLI</Point>
      <Point>MITIN</Point>
      <Point>IMOSO</Point>
      <Point>RABIL</Point>
      <Point>GOYAS</Point>
      <Point>ANILA</Point>
      <Point>MANTA</Point>
      <Point>ONBIK</Point>
      <Point>FRESA</Point>
      <Point>URVEM</Point>
      <Point>XOSUD</Point>
      <Point>XOSAS</Point>
      <Point>XOTKI</Point>
      <Point>AVSAR</Point>

      <Point>SILAC</Point>
      <Point>MORAS</Point>
      <Point>LLANO</Point>
      <Point>HORTA</Point>
      <Point>ERBOS</Point>

      <Point>TAJIN</Point>
      <Point>URLIX</Point>
      <Point>AVALI</Point>
      <Point>RAULS</Point>
      <Point>OTUDI</Point>
      <Point>COAPA</Point>
      <Point>UKROR</Point>
    </Label>
    <Label LabelOrientation="S" HasLeader="false">
      <Point>TIKEB</Point>
      <Point>DATUL</Point>
    </Label>
    <Label LabelOrientation="SW" HasLeader="false">
      <Point>SASUT</Point>
    </Label>

  </Map>
  <Map Type="System" Name="ALL_ROUTES_RNAV" Priority="1" Center="+204657.054-0865400.018">
    <Line Name="L207">IPSEV.L207.CPE</Line>
    <Line Name="L208">DUTNA.L208.MID</Line>
    <Line Name="L209">KEHLI.L209.MID</Line>
    <Line Name="L214">IRDOV.L214.SIGMA</Line>
    <Line Name="L333">PISAD.L333.ILUBA</Line>
    <Line Name="L577">CZM.L577.ILUBA</Line>
    <Line Name="M215">PISAD.M215.MID</Line>
    <Line Name="M219">MYDIA.M219.CUN</Line>
    <Line Name="M345">AXEXO.M345.PAZ</Line>
    <Line Name="M575">CLONN.M575.TAM</Line>
    <Line Name="T12">NABAS.T12.CUL</Line>
    <Line Name="T18">HMO.T18.NABAS</Line>
    <Line Name="T36">CUU.T36.LMM</Line>
    <Line Name="T46">CME.T46.TAM</Line>
    <Line Name="T49">CEN.T49.NABAS</Line>
    <Line Name="T61">TAM.T61.VER</Line>
    <Line Name="UL207">IPSEV.UL207.MUVAP</Line>
    <Line Name="UL208">DUTNA.UL208.MID</Line>
    <Line Name="UL209">KEHLI.UL209.MID</Line>
    <Line Name="UL214">IRDOV.UL214.SIGMA</Line>
    <Line Name="UL308">PBC.UL308.ANREX</Line>
    <Line Name="UL312">TIJ.UL312.KATIS</Line>
    <Line Name="UL318">MEX.UL318.ALSAL</Line>
    <Line Name="UL333">PISAD.UL333.ILUBA</Line>
    <Line Name="UL344">ACA.UL344.NOTOS</Line>
    <Line Name="UL349">VSA.UL349.EMADA</Line>
    <Line Name="UL423">TEQ.UL423.PIXEN</Line>
    <Line Name="UL577">CZM.UL577.ILUBA</Line>
    <Line Name="UL655">PPE.UL655.ASOKU</Line>
    <Line Name="UL674">KEHLI.UL674.ALURU</Line>
    <Line Name="UM206">SESNO.UM206.DASMO</Line>
    <Line Name="UM207">CPE.UM207.ATUTO</Line>
    <Line Name="UM208">CPE.UM208.DASMO</Line>
    <Line Name="UM209">DUTNA.UM209.ANIKO</Line>
    <Line Name="UM210">VER.UM210.MIROX</Line>
    <Line Name="UM215">PISAD.UM215.MID</Line>
    <Line Name="UM219">MYDIA.UM219.CUN</Line>
    <Line Name="UM345">AXEXO.UM345.PAZ</Line>
    <Line Name="UM346">AXOMU.UM346.ULARI</Line>
    <Line Name="UM575">CLONN.UM575.TAM</Line>
    <Line Name="UM580">AVALI.UM580.IRDOV</Line>
    <Line Name="UM782">KEHLI.UM782.TAKUX</Line>
    <Line Name="UM787">MEX.UM787.PILKO</Line>
    <Line Name="UP659">CUA.UP659.TUKEV</Line>
    <Line Name="UQ101">URSUR.UQ101.QET</Line>
    <Line Name="UQ102">VOKOM.UQ102.SLP</Line>
    <Line Name="UQ103">GOLFO.UQ103.AGU</Line>
    <Line Name="UQ104">AVRIL.UQ104.AGU</Line>
    <Line Name="UT1">MOV.UT1.TNY</Line>
    <Line Name="UT2">CUL.UT2.AGU</Line>
    <Line Name="UT3">URKOM.UT3.MOV</Line>
    <Line Name="UT4">TIJ.UT4.PVR</Line>
    <Line Name="UT5">SLW.UT5.ZCL</Line>
    <Line Name="UT6">TIJ.UT6.PVR</Line>
    <Line Name="UT7">UKIVI.UT7.ENEKO</Line>
    <Line Name="UT8">PPE.UT8.LMM</Line>
    <Line Name="UT9">KAVRA.UT9.BECON</Line>
    <Line Name="UT10">PPE.UT10.ZCL</Line>
    <Line Name="UT11">PPE.UT11.CUN</Line>
    <Line Name="UT12">VYLLA.UT12.CUL</Line>
    <Line Name="UT14">SJD.UT14.TNY</Line>
    <Line Name="UT15">LAP.UT15.TNY</Line>
    <Line Name="UT16">BECON.UT16.MZT</Line>
    <Line Name="UT17">LAYKE.UT17.TLC</Line>
    <Line Name="UT18">TIJ.UT18.NABAS</Line>
    <Line Name="UT19">APN.UT19.XUDUN</Line>
    <Line Name="UT20">PAZ.UT20.CZA</Line>
    <Line Name="UT22">MAM.UT22.CZA</Line>
    <Line Name="UT23">TAM.UT23.CUN</Line>
    <Line Name="UT24">UBVOV.UT24.VIVEP</Line>
    <Line Name="UT25">MXL.UT25.LTO</Line>
    <Line Name="UT26">CLONN.UT26.KEKRI</Line>
    <Line Name="UT27">PISAD.UT27.CUN</Line>
    <Line Name="UT28">MEDIR.UT28.XUDUN</Line>
    <Line Name="UT29">URTOK.UT29.SIGMA</Line>
    <Line Name="UT30">CME.UT30.CZM</Line>
    <Line Name="UT31">XUDUN.UT31.PAZ</Line>
    <Line Name="UT34">URTEL.UT34.VOMAR</Line>
    <Line Name="UT35">KEHLI.UT35.ALNUR</Line>
    <Line Name="UT36">CUU.UT36.LMM</Line>
    <Line Name="UT37">SESNO.UT37.PERGO</Line>
    <Line Name="UT41">ASUTA.UT41.CUU</Line>
    <Line Name="UT42">APN.UT42.MID</Line>
    <Line Name="UT43">IRDOV.UT43.VOMAR</Line>
    <Line Name="UT44">GDL.UT44.MTY</Line>
    <Line Name="UT45">IRDOV.UT45.OMVIP</Line>
    <Line Name="UT46">CME.UT46.TAM</Line>
    <Line Name="UT48">MAM.UT48.AVALI</Line>
    <Line Name="UT49">CEN.UT49.DGO</Line>
    <Line Name="UT50">TAGMO.UT50.ASUTA</Line>
    <Line Name="UT60">BJX.UT60.AXASA</Line>
    <Line Name="UT61">TAM.UT61.VER</Line>
    <Line Name="UT71">SLW.UT71.TENAY</Line>
    <Line Name="UT73">PVR.UT73.SJD</Line>
    <Line Name="UT75">CSL.UT75.PVR</Line>
    <Symbol Type="SolidTriangle">
    </Symbol>
    <Symbol Type="HollowStar">
      <Point>MYDIA</Point>
      <Point>LENUK</Point>
      <Point>PIXEN</Point>
    </Symbol>
    <Symbol Type="SolidStar">
      <Point>IPSEV</Point>
      <Point>DUTNA</Point>
      <Point>IRDOV</Point>
      <Point>PISAD</Point>
      <Point>ULARI</Point>
      <Point>TAKUX</Point>
      <Point>DASMO</Point>
      <Point>ATUTO</Point>
      <Point>EMADA</Point>
      <Point>PILKO</Point>
      <Point>MIROX</Point>
      <Point>ALSAL</Point>
      <Point>TUKEV</Point>
      <Point>ANREX</Point>
      <Point>NOTOS</Point>
      <Point>KATIS</Point>
      <Point>BERAN</Point>
      <Point>ULAPA</Point>
      <Point>AUTLA</Point>
      <Point>VOGON</Point>
      <Point>UGERO</Point>
      <Point>DUTRO</Point>
      <Point>AVIVI</Point>
      <Point>ELURA</Point>
      <Point>NUBIT</Point>
      <Point>UBVOV</Point>
      <Point>TADET</Point>
      <Point>LIDAM</Point>
      <Point>DUSAT</Point>
      <Point>NOTEN</Point>
      <Point>GABAT</Point>
      <Point>MATOL</Point>
    </Symbol>
  </Map>
  <Map Type="System" Name="ALL_POINTS_RNAV" Priority="1" Center="+204657.054-0865400.018">
    <Label HasLeader="false">
      <!--MMID-->
      <Point>MYDIA</Point>
      <Point>LENUK</Point>
      <Point>PIXEN</Point>

      <Point>IPSEV</Point>
      <Point>DUTNA</Point>
      <Point>IRDOV</Point>
      <Point>PISAD</Point>
      <Point>ULARI</Point>
      <Point>TAKUX</Point>
      <Point>DASMO</Point>
      <Point>ATUTO</Point>
      <Point>EMADA</Point>
      <Point>PILKO</Point>
      <Point>MIROX</Point>
      <Point>ALSAL</Point>
      <Point>TUKEV</Point>
      <Point>ANREX</Point>
      <Point>NOTOS</Point>
      <Point>KATIS</Point>
      <Point>BERAN</Point>
      <Point>ULAPA</Point>
      <Point>AUTLA</Point>
      <Point>VOGON</Point>
      <Point>UGERO</Point>
      <Point>DUTRO</Point>
      <Point>AVIVI</Point>
      <Point>ELURA</Point>
      <Point>NUBIT</Point>
      <Point>UBVOV</Point>
      <Point>TADET</Point>
      <Point>LIDAM</Point>
      <Point>DUSAT</Point>
      <Point>NOTEN</Point>
      <Point>GABAT</Point>
      <Point>MATOL</Point>
    </Label>
  </Map>
</Maps>