<?xml version="1.0" encoding="utf-8"?>
<Maps>
  <Map Type="System2" Name="Aeropuerto - Pista" Priority="1">
    <Runway Name="09/27">
      <Threshold Name="09" Position="+203713.30-1001206.700" />
      <Threshold Name="27" Position="+203651.70-1001009.600" />
    </Runway>
  </Map>
  <Map Type="System2" Name="Aeropuerto - Area Terminal (TMA)" Priority="1">
    <Line Pattern="Dashed">
+213704.000-1000557.000/
+213638.345-1000426.498/
+213613.778-1000107.124/
+213539.479-0995749.397/
+213455.541-0995433.859/
+213402.086-0995121.045/
+213259.258-0994811.485/
+213147.232-0994505.698/
+213026.203-0994204.193/
+212856.395-0993907.468/
+212718.054-0993616.006/
+212531.448-0993330.279/
+212336.870-0993050.740/
+212134.635-0992817.826/
+211925.076-0992551.958/
+211708.550-0992333.533/
+211445.431-0992122.933/
+211216.111-0991920.514/
+210940.998-0991726.613/
+210700.519-0991541.541/
+210415.113-0991405.587/
+210125.233-0991239.014/
+205831.346-0991122.058/
+205533.927-0991014.931/
+205233.464-0990917.818/
+204930.450-0990830.873/
+204625.387-0990754.226/
+204318.783-0990727.978/
+204011.148-0990712.201/
+203702.999-0990706.937/
+203354.849-0990712.201/
+203047.214-0990727.978/
+202740.610-0990754.226/
+202631.000-0990812.000/
+202714.000-0993059.000/
+195102.000-1000654.000/
+194522.000-1000706.000/
+203221.000-1005513.000/
+212417.000-1003807.000/
+213704.000-1000557.000</Line>
  </Map>
  <Map Type="System" Name="Aeropuerto - Zona de Control (CTR)" Priority="1">
  	<Line Pattern="Dashed">
+204957.507-1001010.067/
+204952.184-1000926.869/
+204944.753-1000844.028/
+204935.233-1000801.662/
+204923.651-1000719.885/
+204910.038-1000638.814/
+204854.432-1000558.560/
+204836.876-1000519.234/
+204817.418-1000440.944/
+204756.110-1000403.794/
+204733.012-1000327.886/
+204708.187-1000253.319/
+204641.703-1000220.188/
+204613.632-1000148.583/
+204544.051-1000118.591/
+204513.042-1000050.294/
+204440.689-1000023.770/
+204407.082-0995959.092/
+204332.311-0995936.326/
+204256.473-0995915.536/
+204219.666-0995856.779/
+204141.990-0995840.105/
+204103.550-0995825.561/
+204024.449-0995813.186/
+203944.796-0995803.015/
+203904.699-0995755.075/
+203824.268-0995749.388/
+203743.614-0995745.969/
+203702.849-0995744.829/
+203622.083-0995745.969/
+203541.429-0995749.388/
+203500.998-0995755.075/
+203420.901-0995803.015/
+203341.248-0995813.186/
+203302.147-0995825.561/
+203223.707-0995840.105/
+203146.031-0995856.779/
+203109.224-0995915.536/
+203033.386-0995936.326/
+202958.615-0995959.092/
+202925.008-1000023.770/
+202852.655-1000050.294/
+202821.646-1000118.591/
+202752.065-1000148.583/
+202723.994-1000220.188/
+202657.510-1000253.319/
+202632.685-1000327.886/
+202609.587-1000403.794/
+202548.279-1000440.944/
+202528.821-1000519.234/
+202511.265-1000558.560/
+202455.659-1000638.814/
+202442.046-1000719.885/
+202430.464-1000801.662/
+202420.944-1000844.028/
+202413.513-1000926.869/
+202408.190-1001010.067/
+202404.990-1001053.503/
+202403.923-1001137.059/
+202404.990-1001220.614/
+202408.190-1001304.050/
+202413.513-1001347.248/
+202420.944-1001430.089/
+202430.464-1001512.455/
+202442.046-1001554.232/
+202455.659-1001635.303/
+202511.265-1001715.557/
+202528.821-1001754.883/
+202548.279-1001833.173/
+202609.587-1001910.323/
+202632.685-1001946.231/
+202657.510-1002020.798/
+202723.994-1002053.929/
+202752.065-1002125.534/
+202821.646-1002155.526/
+202852.655-1002223.823/
+202925.008-1002250.347/
+202958.615-1002315.025/
+203033.386-1002337.791/
+203109.224-1002358.581/
+203146.031-1002417.338/
+203223.707-1002434.012/
+203302.147-1002448.556/
+203341.248-1002500.931/
+203420.901-1002511.102/
+203500.998-1002519.042/
+203541.429-1002524.729/
+203622.083-1002528.148/
+203702.849-1002529.288/
+203743.614-1002528.148/
+203824.268-1002524.729/
+203904.699-1002519.042/
+203944.796-1002511.102/
+204024.449-1002500.931/
+204103.550-1002448.556/
+204141.990-1002434.012/
+204219.666-1002417.338/
+204256.473-1002358.581/
+204332.311-1002337.791/
+204407.082-1002315.025/
+204440.689-1002250.347/
+204513.042-1002223.823/
+204544.051-1002155.526/
+204613.632-1002125.534/
+204641.703-1002053.929/
+204708.187-1002020.798/
+204733.012-1001946.231/
+204756.110-1001910.323/
+204817.418-1001833.173/
+204836.876-1001754.883/
+204854.432-1001715.557/
+204910.038-1001635.303/
+204923.651-1001554.232/
+204935.233-1001512.455/
+204944.753-1001430.089/
+204952.184-1001347.248/
+204957.507-1001304.050/
+205000.707-1001220.614/
+205001.774-1001137.059/
+205000.707-1001053.503/
+204957.507-1001010.067</Line>
  </Map>
  <Map Type="System" Name="Aeropuerto - Fijos 09" Priority="1" Center="+203704.000-1001112.000">
    <Symbol Type="SolidTriangle">
      <Point>DUPUD</Point>
      <Point>FRESA</Point>
      <Point>ONBIK</Point>
      <Point>OTRUD</Point>
      <Point>PIGVU</Point>
      <Point>URNAT</Point>
      <Point>XOSAS</Point>
      <Point>XUKVA</Point>
    </Symbol>
  </Map>
  <Map Type="System" Name="Aeropuerto - Fijos 09 (Nombres)" Priority="1" Center="+203704.000-1001112.000">
    <Label HasLeader="false">
      <Point>DUPUD</Point>
      <Point>FRESA</Point>
      <Point>ONBIK</Point>
      <Point>OTRUD</Point>
      <Point>PIGVU</Point>
      <Point>URNAT</Point>
      <Point>XOSAS</Point>
      <Point>XUKVA</Point>
    </Label>
  </Map>
  <Map Type="System" Name="Aeropuerto - Fijos 27" Priority="1" Center="+203704.000-1001112.000">
    <Symbol Type="SolidTriangle">
      <Point>DAVUL</Point>
      <Point>DUPUD</Point>
      <Point>OTRUD</Point>
      <Point>ROGDI</Point>
      <Point>XUKVA</Point>
    </Symbol>
  </Map>
  <Map Type="System" Name="Aeropuerto - Fijos 27 (Nombres)" Priority="1" Center="+203704.000-1001112.000">
    <Label HasLeader="false">
      <Point>DAVUL</Point>
      <Point>DUPUD</Point>
      <Point>OTRUD</Point>
      <Point>ROGDI</Point>
      <Point>XUKVA</Point>
    </Label>
  </Map>
</Maps>
